[
    {
        "username": "testtest1",
        "password": "$2b$10$itXxRFinrxVgCeXEBJQakOeYTNH2BVQVTUM.kt2.kGmD4gLKjtZVi",
        "isShipper": true,
        "isCourier": false,
        "city": "Denver",
        "state": "CO"
    },
    {
        "username": "testtest2",
        "password": "$2b$10$itXxRFinrxVgCeXEBJQakOpaMNacx4/d1CmFjcDt2ciXUR1g0/8E2",
        "isShipper": false,
        "isCourier": true,
        "city": "Nashville",
        "state": "TN"
    },
    {
        "username": "testtest3",
        "password": "$2b$10$itXxRFinrxVgCeXEBJQakO/KEIVIaoNqLHeLsbbjC8he5R.GqMLV2",
        "isShipper": false,
        "isCourier": true,
        "city": "Nashville",
        "state": "TN"
    },
    {
        "username": "testtest4",
        "password": "$2b$10$itXxRFinrxVgCeXEBJQakO2UzIxHo1ozbon526qrgqNPwWNSt78ym",
        "isShipper": false,
        "isCourier": true,
        "city": "Nashville",
        "state": "TN"
    },
    {
        "username": "testtest5",
        "password": "$2b$10$itXxRFinrxVgCeXEBJQakO5PSto7wgrWv3Gpc2pCrnuyD7iy0bwla",
        "isShipper": true,
        "isCourier": false,
        "city": "Nashville",
        "state": "TN"
    },
    {
        "username": "testtest6",
        "password": "$2b$10$itXxRFinrxVgCeXEBJQakO7Y9vEDyO.6J7R/r9naDvx7U9vauUSQm",
        "isShipper": true,
        "isCourier": false,
        "city": "Nashville",
        "state": "TN"
    }
]